Lab10/ring_counter_4bit.v
module ring_counter_4bit(Q,clk,clr);
input clk,clr;
output reg [3:0]Q;

always @(posedge clk,posedge clr)begin
    if(clr) Q<=4'b1000;
    else begin
        Q[3]<=Q[0];
        Q[2]<=Q[3];
        Q[1]<=Q[2];
        Q[0]<=Q[1];
    end
end
endmodule

Lab10/ring_counter_4bit_tb.v
`include "ring_counter_4bit.v"
`timescale 1ns/1ns

module ring_counter_4bit_tb();

reg clk,clr;
wire [3:0]Q;

ring_counter_4bit ring_counter_4bit_ins(Q,clk,clr);

initial begin
    $dumpfile("ring_counter_4bit_tb.vcd");
    $dumpvars(0,ring_counter_4bit_tb);
end

initial begin
    clk = 0;
    forever #2 clk = ~clk;
end

initial begin
    clr = 1; #4;
    clr = 0; #30;
    $finish;
end
endmodule

Lab10/ring_counter_4bit_tb.vcd
$date
	Wed Oct 01 19:22:50 2025
$end
$version
	Icarus Verilog
$end
$timescale
	1ns
$end
$scope module ring_counter_4bit_tb $end
$var wire 4 ! Q [3:0] $end
$var reg 1 " clk $end
$var reg 1 # clr $end
$scope module ring_counter_4bit_ins $end
$var wire 1 " clk $end
$var wire 1 # clr $end
$var reg 4 $ Q [3:0] $end
$upscope $end
$upscope $end
$enddefinitions $end
$comment Show the parameter values. $end
$dumpall
$end
#0
$dumpvars
b1000 $
1#
0"
b1000 !
$end
#2
1"
#4
0"
0#
#6
b100 !
b100 $
1"
#8
0"
#10
b10 !
b10 $
1"
#12
0"
#14
b1 !
b1 $
1"
#16
0"
#18
b1000 !
b1000 $
1"
#20
0"
#22
b100 !
b100 $
1"
#24
0"
#26
b10 !
b10 $
1"
#28
0"
#30
b1 !
b1 $
1"
#32
0"
#34
b1000 !
b1000 $
1"
