Lab9/JKFF.v
module JKFF(J,K,clk,Q,reset);

input J,K,clk,reset;
output reg Q;

always @(posedge clk,posedge reset)begin
    if(reset) Q<=0;
    else begin
        if(J==0)begin
            if(K==0) Q<=Q;
            else Q<=0;
        end
        else if(J==1)begin
            if(K==0) Q<=1;
            else Q<=~Q;
        end
    end
end
endmodule

Lab9/Q1.v
`include "JKFF.v"
module Q1(E,x,clk,A,B,reset);
input E,x,clk,reset;
output A,B;

wire Ja,Ka,Jb,Kb;

assign Ja = (B&E&x)|((~B)&E&(~x));
assign Ka = (B&E&x)|((~B)&E&(~x));
assign Jb = E;
assign Kb = E;

JKFF JKFF_A(Ja,Ka,clk,A,reset);
JKFF JKFF_B(Jb,Kb,clk,B,reset);
endmodule

Lab9/Q1_tb.v
`include "Q1.v"
`timescale 1ns/1ns

module Q1_tb();

reg E,x,clk,reset;
wire A,B;

Q1 Q1_ins(E,x,clk,A,B,reset);

initial begin
    $dumpfile("Q1_tb.vcd");
    $dumpvars(0,Q1_tb);
end

initial begin
    clk = 0;
    forever #2 clk = ~clk;
end

initial begin
    E = 0; x = 0; reset = 1; #10;
    E = 0; x = 0; reset = 0; #10;
    E = 0; x = 1; reset = 0; #10;
    E = 1; x = 0; reset = 0; #10;
    E = 1; x = 1; reset = 0; #10;
    E = 0; x = 0; reset = 0; #10;
    E = 0; x = 1; reset = 0; #10;
    E = 1; x = 0; reset = 0; #10;
    E = 1; x = 1; reset = 0; #10;
    $finish;
end
endmodule

Lab9/Q1_tb.vcd
$date
	Wed Oct 01 18:05:21 2025
$end
$version
	Icarus Verilog
$end
$timescale
	1ns
$end
$scope module Q1_tb $end
$var wire 1 ! B $end
$var wire 1 " A $end
$var reg 1 # E $end
$var reg 1 $ clk $end
$var reg 1 % reset $end
$var reg 1 & x $end
$scope module Q1_ins $end
$var wire 1 # E $end
$var wire 1 ' Ja $end
$var wire 1 ( Jb $end
$var wire 1 ) Ka $end
$var wire 1 * Kb $end
$var wire 1 $ clk $end
$var wire 1 % reset $end
$var wire 1 & x $end
$var wire 1 ! B $end
$var wire 1 " A $end
$scope module JKFF_A $end
$var wire 1 ' J $end
$var wire 1 ) K $end
$var wire 1 $ clk $end
$var wire 1 % reset $end
$var reg 1 " Q $end
$upscope $end
$scope module JKFF_B $end
$var wire 1 ( J $end
$var wire 1 * K $end
$var wire 1 $ clk $end
$var wire 1 % reset $end
$var reg 1 ! Q $end
$upscope $end
$upscope $end
$upscope $end
$enddefinitions $end
$comment Show the parameter values. $end
$dumpall
$end
#0
$dumpvars
0*
0)
0(
0'
0&
1%
0$
0#
0"
0!
$end
#2
1$
#4
0$
#6
1$
#8
0$
#10
1$
0%
#12
0$
#14
1$
#16
0$
#18
1$
#20
0$
1&
#22
1$
#24
0$
#26
1$
#28
0$
#30
1!
0'
0)
1$
0&
1(
1*
1#
#32
0$
#34
1)
1'
0!
1$
#36
0$
#38
0)
0'
1"
1!
1$
#40
1'
1)
0$
1&
#42
0)
0'
0!
0"
1$
#44
0$
#46
1)
1'
1!
1$
#48
0$
#50
1"
0'
0)
1$
0&
0(
0*
0#
#52
0$
#54
1$
#56
0$
#58
1$
#60
0$
1&
#62
1$
#64
0$
#66
1$
#68
0$
#70
1)
1'
0!
1$
0&
1(
1*
1#
#72
0$
#74
0)
0'
1!
0"
1$
#76
0$
#78
1)
1'
0!
1$
#80
0'
0)
0$
1&
#82
1)
1'
1!
1$
#84
0$
#86
0)
0'
1"
0!
1$
#88
0$
#90
1)
1'
1!
1$
