Lab8/shiftReg6Bit.v
module shiftReg6Bit(W,clk,Q);

input W,clk;
output reg[5:0]Q;

always@(posedge clk)begin
    Q[5]<=W;
    Q[4]<=Q[5];
    Q[3]<=Q[4];
    Q[2]<=Q[3];
    Q[1]<=Q[2];
    Q[0]<=Q[1];
end
endmodule

Lab8/shiftReg6Bit_tb.v
`include "shiftReg6Bit.v"
`timescale 1ns/1ns

module shiftReg6Bit_tb();

reg W,clk;
wire [5:0]Q;

shiftReg6Bit shiftReg6Bit_ins(W,clk,Q);

initial begin
    $dumpfile("shiftReg6Bit_tb.vcd");
    $dumpvars(0,shiftReg6Bit_tb);
end

initial begin
    clk = 0;
    forever #10 clk = ~clk;
end

initial begin
    W = 1'b0;  #10;
    W = 1'b1;  #10;   
    W = 1'b0;  #20;
    W = 1'b1;  #20;
    W = 1'b1;  #20;
    W = 1'b0;  #20;
    W = 1'b0;  #20;  
    $finish;
end
endmodule

Lab8/shiftReg6Bit_tb.vcd
$date
	Mon Sep 29 00:49:57 2025
$end
$version
	Icarus Verilog
$end
$timescale
	1ns
$end
$scope module shiftReg6Bit_tb $end
$var wire 6 ! Q [5:0] $end
$var reg 1 " W $end
$var reg 1 # clk $end
$scope module shiftReg6Bit_ins $end
$var wire 1 " W $end
$var wire 1 # clk $end
$var reg 6 $ Q [5:0] $end
$upscope $end
$upscope $end
$enddefinitions $end
$comment Show the parameter values. $end
$dumpall
$end
#0
$dumpvars
bx $
0#
0"
bx !
$end
#10
b1xxxxx !
b1xxxxx $
1"
1#
#20
0"
0#
#30
b1xxxx !
b1xxxx $
1#
#40
0#
1"
#50
b101xxx !
b101xxx $
1#
#60
0#
#70
b1101xx !
b1101xx $
1#
#80
0#
0"
#90
b1101x !
b1101x $
1#
#100
0#
#110
b1101 !
b1101 $
1#
