Lab4/full_adder.v
module full_adder(a,b,cin,s,cout);
input a,b,cin;
output s,cout;
assign s = a^b^cin;
assign cout = (a&b)|(b&cin)|(a&cin);
endmodule

Lab4/full_adder_tb.v
`timescale 1ns/1ns
`include "full_adder.v"

module full_adder_tb();
reg a,b,c;
wire s,cout;

full_adder fa_instance(a,b,c,s,cout);

initial begin

$dumpfile("full_adder_tb.vcd");
$dumpvars(0,full_adder_tb);
a = 0; b = 0; c = 0;
#10;
a = 0; b = 0; c = 1;
#10;
a = 0; b = 1; c = 0;
#10;
a = 0; b = 1 ; c = 1;
#10;
a = 1; b = 0; c = 0;
#10;
a = 1; b = 0; c = 1;
#10; 
a = 1; b = 1; c = 0;
#10;
a = 1; b = 1; c = 1;
#10;
$display("Test completed successfully.");
$finish;
end
endmodule

Lab4/full_adder_tb.vcd
$date
	Thu Aug 28 21:03:38 2025
$end
$version
	Icarus Verilog
$end
$timescale
	1ns
$end
$scope module full_adder_tb $end
$var wire 1 ! s $end
$var wire 1 " cout $end
$var reg 1 # a $end
$var reg 1 $ b $end
$var reg 1 % c $end
$scope module fa_instance $end
$var wire 1 # a $end
$var wire 1 $ b $end
$var wire 1 % cin $end
$var wire 1 " cout $end
$var wire 1 ! s $end
$upscope $end
$upscope $end
$enddefinitions $end
$comment Show the parameter values. $end
$dumpall
$end
#0
$dumpvars
0%
0$
0#
0"
0!
$end
#10
1!
1%
#20
0%
1$
#30
1"
0!
1%
#40
0"
1!
0%
0$
1#
#50
1"
0!
1%
#60
0%
1$
#70
1!
1%
