Lab5/MUX2to1.v
module MUX2to1(w,s0,f);
input [0:1] w;
input s0;
output reg f;

always @(w,s0) begin
    if(s0==0)
        f = w[0];
    else if(s0==1)
        f = w[1];
end

endmodule

Lab5/MUX4to1.v
`include "MUX2to1.v"
`timescale 1ns/1ns

module MUX4to1(w,s,f);

input[0:3] w;
input [1:0] s;
output f;
wire [0:1] c;
MUX2to1 MUX2to1_stage1a(w[0:1],s[0],c[0]);
MUX2to1 MUX2to1_stage1b(w[2:3],s[0],c[1]);
MUX2to1 MUX2to1_stage2(c,s[1],f);
endmodule

Lab5/MUX16to1.v
`include "MUX4to1.v"
module MUX16to1(w,s,f);

input[0:15] w;
input[3:0] s;
wire[0:3] c;
output f;

MUX4to1 MUX4to1_stage1a(w[0:3],s[1:0],c[0]);
MUX4to1 MUX4to1_stage1b(w[4:7],s[1:0],c[1]);
MUX4to1 MUX4to1_stage1c(w[8:11],s[1:0],c[2]);
MUX4to1 MUX4to1_stage1d(w[12:15],s[1:0],c[3]);
MUX4to1 MUX4to1_stage2(c,s[3:2],f);

endmodule

Lab5/MUX16to1_tb.v
`include "MUX16to1.v"
`timescale 1ns/1ns

module MUX16to1_tb();

reg [0:15] w;
reg [3:0] s;
wire f;

MUX16to1 MUX16to1_instance(w,s,f);

initial begin
    $dumpfile("MUX16to1_tb.vcd");
    $dumpvars(0,MUX16to1_tb);

    // 
    
    for (integer i = 0; i < 16; i = i + 1) begin
        w = 16'hACF1; s= i;
        #10;   
    end
    
    for (integer i = 0; i < 16; i = i + 1) begin
        w = 16'hCBE3; s= i;
        #10;   
    end

end
endmodule

Lab5/MUX16to1_tb.vcd
$date
	Sun Aug 31 23:56:20 2025
$end
$version
	Icarus Verilog
$end
$timescale
	1ns
$end
$scope module MUX16to1_tb $end
$var wire 1 ! f $end
$var reg 4 " s [3:0] $end
$var reg 16 # w [0:15] $end
$scope module MUX16to1_instance $end
$var wire 4 $ s [3:0] $end
$var wire 16 % w [0:15] $end
$var wire 1 ! f $end
$var wire 4 & c [0:3] $end
$scope module MUX4to1_stage1a $end
$var wire 2 ' s [1:0] $end
$var wire 4 ( w [0:3] $end
$var wire 1 ) f $end
$var wire 2 * c [0:1] $end
$scope module MUX2to1_stage1a $end
$var wire 1 + s0 $end
$var wire 2 , w [0:1] $end
$var reg 1 - f $end
$upscope $end
$scope module MUX2to1_stage1b $end
$var wire 1 . s0 $end
$var wire 2 / w [0:1] $end
$var reg 1 0 f $end
$upscope $end
$scope module MUX2to1_stage2 $end
$var wire 1 1 s0 $end
$var wire 2 2 w [0:1] $end
$var reg 1 ) f $end
$upscope $end
$upscope $end
$scope module MUX4to1_stage1b $end
$var wire 2 3 s [1:0] $end
$var wire 4 4 w [0:3] $end
$var wire 1 5 f $end
$var wire 2 6 c [0:1] $end
$scope module MUX2to1_stage1a $end
$var wire 1 7 s0 $end
$var wire 2 8 w [0:1] $end
$var reg 1 9 f $end
$upscope $end
$scope module MUX2to1_stage1b $end
$var wire 1 : s0 $end
$var wire 2 ; w [0:1] $end
$var reg 1 < f $end
$upscope $end
$scope module MUX2to1_stage2 $end
$var wire 1 = s0 $end
$var wire 2 > w [0:1] $end
$var reg 1 5 f $end
$upscope $end
$upscope $end
$scope module MUX4to1_stage1c $end
$var wire 2 ? s [1:0] $end
$var wire 4 @ w [0:3] $end
$var wire 1 A f $end
$var wire 2 B c [0:1] $end
$scope module MUX2to1_stage1a $end
$var wire 1 C s0 $end
$var wire 2 D w [0:1] $end
$var reg 1 E f $end
$upscope $end
$scope module MUX2to1_stage1b $end
$var wire 1 F s0 $end
$var wire 2 G w [0:1] $end
$var reg 1 H f $end
$upscope $end
$scope module MUX2to1_stage2 $end
$var wire 1 I s0 $end
$var wire 2 J w [0:1] $end
$var reg 1 A f $end
$upscope $end
$upscope $end
$scope module MUX4to1_stage1d $end
$var wire 2 K s [1:0] $end
$var wire 4 L w [0:3] $end
$var wire 1 M f $end
$var wire 2 N c [0:1] $end
$scope module MUX2to1_stage1a $end
$var wire 1 O s0 $end
$var wire 2 P w [0:1] $end
$var reg 1 Q f $end
$upscope $end
$scope module MUX2to1_stage1b $end
$var wire 1 R s0 $end
$var wire 2 S w [0:1] $end
$var reg 1 T f $end
$upscope $end
$scope module MUX2to1_stage2 $end
$var wire 1 U s0 $end
$var wire 2 V w [0:1] $end
$var reg 1 M f $end
$upscope $end
$upscope $end
$scope module MUX4to1_stage2 $end
$var wire 2 W s [1:0] $end
$var wire 4 X w [0:3] $end
$var wire 1 ! f $end
$var wire 2 Y c [0:1] $end
$scope module MUX2to1_stage1a $end
$var wire 1 Z s0 $end
$var wire 2 [ w [0:1] $end
$var reg 1 \ f $end
$upscope $end
$scope module MUX2to1_stage1b $end
$var wire 1 ] s0 $end
$var wire 2 ^ w [0:1] $end
$var reg 1 _ f $end
$upscope $end
$scope module MUX2to1_stage2 $end
$var wire 1 ` s0 $end
$var wire 2 a w [0:1] $end
$var reg 1 ! f $end
$upscope $end
$upscope $end
$upscope $end
$scope begin $ivl_for_loop0 $end
$var integer 32 b i [31:0] $end
$upscope $end
$scope begin $ivl_for_loop1 $end
$var integer 32 c i [31:0] $end
$upscope $end
$upscope $end
$enddefinitions $end
$comment Show the parameter values. $end
$dumpall
$end
#0
$dumpvars
bx c
b0 b
b11 a
0`
1_
b10 ^
0]
1\
b11 [
0Z
b11 Y
b1110 X
b0 W
b0 V
0U
0T
b1 S
0R
0Q
b0 P
0O
b0 N
0M
b1 L
b0 K
b11 J
0I
1H
b11 G
0F
1E
b11 D
0C
b11 B
1A
b1111 @
b0 ?
b10 >
0=
0<
b0 ;
0:
19
b11 8
07
b10 6
15
b1100 4
b0 3
b11 2
01
10
b10 /
0.
1-
b10 ,
0+
b11 *
1)
b1010 (
b0 '
b1110 &
b1010110011110001 %
b0 $
b1010110011110001 #
b0 "
1!
$end
#10
0!
b1 Y
b1 a
0\
b1 [
b110 &
b110 X
0)
0-
b0 *
b0 2
00
b1 N
b1 V
1T
1+
1.
17
1:
1C
1F
1O
1R
b1 '
b1 3
b1 ?
b1 K
b1 "
b1 $
b1 b
#20
1!
b11 Y
b11 a
1\
1)
b10 [
b10 ^
1-
b11 *
b11 2
10
05
b0 N
b0 V
0T
b1010 &
b1010 X
0M
0+
0.
11
07
0:
1=
0C
0F
1I
0O
0R
1U
b10 '
b10 3
b10 ?
b10 K
b10 "
b10 $
b10 b
#30
0!
b1 Y
b1 a
0\
b0 [
b11 ^
0)
b11 &
b11 X
1M
0-
b0 *
b0 2
00
b1 N
b1 V
1T
1+
1.
17
1:
1C
1F
1O
1R
b11 '
b11 3
b11 ?
b11 K
b11 "
b11 $
b11 b
#40
1!
1\
b10 Y
b10 a
0_
1)
b11 [
b10 ^
1-
b11 *
b11 2
10
15
b0 N
b0 V
0T
b1110 &
b1110 X
0M
0+
0.
01
07
0:
0=
0C
0F
0I
0O
0R
0U
1Z
1]
b0 '
b0 3
b0 ?
b0 K
b1 W
b100 "
b100 $
b100 b
#50
b1 [
b110 &
b110 X
0)
0-
b0 *
b0 2
00
b1 N
b1 V
1T
1+
1.
17
1:
1C
1F
1O
1R
b1 '
b1 3
b1 ?
b1 K
b101 "
b101 $
b101 b
#60
0!
0\
b0 Y
b0 a
0_
1)
b10 [
b10 ^
1-
b11 *
b11 2
10
05
b0 N
b0 V
0T
b1010 &
b1010 X
0M
0+
0.
11
07
0:
1=
0C
0F
1I
0O
0R
1U
b10 '
b10 3
b10 ?
b10 K
b110 "
b110 $
b110 b
#70
b1 Y
b1 a
1_
b0 [
b11 ^
0)
b11 &
b11 X
1M
0-
b0 *
b0 2
00
b1 N
b1 V
1T
1+
1.
17
1:
1C
1F
1O
1R
b11 '
b11 3
b11 ?
b11 K
b111 "
b111 $
b111 b
#80
b11 Y
b11 a
1\
1)
b11 [
b10 ^
1-
b11 *
b11 2
10
15
b0 N
b0 V
0T
b1110 &
b1110 X
0M
1!
0+
0.
01
07
0:
0=
0C
0F
0I
0O
0R
0U
0Z
0]
1`
b0 '
b0 3
b0 ?
b0 K
b10 W
b1000 "
b1000 $
b1000 b
#90
b1 Y
b1 a
0\
b1 [
b110 &
b110 X
0)
0-
b0 *
b0 2
00
b1 N
b1 V
1T
1+
1.
17
1:
1C
1F
1O
1R
b1 '
b1 3
b1 ?
b1 K
b1001 "
b1001 $
b1001 b
#100
b11 Y
b11 a
1\
1)
b10 [
b10 ^
1-
b11 *
b11 2
10
05
b0 N
b0 V
0T
b1010 &
b1010 X
0M
0+
0.
11
07
0:
1=
0C
0F
1I
0O
0R
1U
b10 '
b10 3
b10 ?
b10 K
b1010 "
b1010 $
b1010 b
#110
b1 Y
b1 a
0\
b0 [
b11 ^
0)
b11 &
b11 X
1M
0-
b0 *
b0 2
00
b1 N
b1 V
1T
1+
1.
17
1:
1C
1F
1O
1R
b11 '
b11 3
b11 ?
b11 K
b1011 "
b1011 $
b1011 b
#120
0!
1\
b10 Y
b10 a
0_
1)
b11 [
b10 ^
1-
b11 *
b11 2
10
15
b0 N
b0 V
0T
b1110 &
b1110 X
0M
0+
0.
01
07
0:
0=
0C
0F
0I
0O
0R
0U
1Z
1]
b0 '
b0 3
b0 ?
b0 K
b11 W
b1100 "
b1100 $
b1100 b
#130
b1 [
b110 &
b110 X
0)
0-
b0 *
b0 2
00
b1 N
b1 V
1T
1+
1.
17
1:
1C
1F
1O
1R
b1 '
b1 3
b1 ?
b1 K
b1101 "
b1101 $
b1101 b
#140
0!
0\
b0 Y
b0 a
0_
1)
b10 [
b10 ^
1-
b11 *
b11 2
10
05
b0 N
b0 V
0T
b1010 &
b1010 X
0M
0+
0.
11
07
0:
1=
0C
0F
1I
0O
0R
1U
b10 '
b10 3
b10 ?
b10 K
b1110 "
b1110 $
b1110 b
#150
1!
b1 Y
b1 a
1_
b0 [
b11 ^
0)
b11 &
b11 X
1M
0-
b0 *
b0 2
00
b1 N
b1 V
1T
1+
1.
17
1:
1C
1F
1O
1R
b11 '
b11 3
b11 ?
b11 K
b1111 "
b1111 $
b1111 b
#160
b11 Y
b11 a
1\
b11 [
b10 ^
1)
15
b1110 &
b1110 X
0M
1!
b10 *
b10 2
1-
b11 6
b11 >
1<
0+
0.
01
07
0:
0=
0C
0F
0I
0O
0R
0U
0Z
0]
0`
b11 ,
b0 /
b10 8
b11 ;
b10 G
b11 S
b0 '
b0 3
b0 ?
b0 K
b0 W
b1100 (
b1011 4
b1110 @
b11 L
b0 "
b0 $
b1100101111100011 #
b1100101111100011 %
b0 c
b10000 b
#170
b10 [
b1010 &
b1010 X
05
b1 6
b1 >
09
b10 B
b10 J
0H
1+
1.
17
1:
1C
1F
1O
1R
b1 '
b1 3
b1 ?
b1 K
b1 "
b1 $
b1 c
#180
0!
0\
b1 Y
b1 a
1_
b1 [
b11 ^
0)
b11 6
b11 >
19
15
b11 B
b11 J
1H
1A
b111 &
b111 X
1M
0+
0.
11
07
0:
1=
0C
0F
1I
0O
0R
1U
b10 '
b10 3
b10 ?
b10 K
b10 "
b10 $
b10 c
#190
b0 Y
b0 a
0_
b1 ^
b101 &
b101 X
0A
b1 6
b1 >
09
b10 B
b10 J
0H
1+
1.
17
1:
1C
1F
1O
1R
b11 '
b11 3
b11 ?
b11 K
b11 "
b11 $
b11 c
#200
b11 [
b10 ^
1!
1)
b11 6
b11 >
19
15
b11 B
b11 J
1H
1A
b1110 &
b1110 X
0M
1\
b10 Y
b10 a
0_
0+
0.
01
07
0:
0=
0C
0F
0I
0O
0R
0U
1Z
1]
b0 '
b0 3
b0 ?
b0 K
b1 W
b100 "
b100 $
b100 c
#210
0!
b0 Y
b0 a
0\
b10 [
b1010 &
b1010 X
05
b1 6
b1 >
09
b10 B
b10 J
0H
1+
1.
17
1:
1C
1F
1O
1R
b1 '
b1 3
b1 ?
b1 K
b101 "
b101 $
b101 c
#220
1!
1\
b11 Y
b11 a
1_
b1 [
b11 ^
0)
b11 6
b11 >
19
15
b11 B
b11 J
1H
1A
b111 &
b111 X
1M
0+
0.
11
07
0:
1=
0C
0F
1I
0O
0R
1U
b10 '
b10 3
b10 ?
b10 K
b110 "
b110 $
b110 c
#230
b1 ^
b101 &
b101 X
0A
b1 6
b1 >
09
b10 B
b10 J
0H
1+
1.
17
1:
1C
1F
1O
1R
b11 '
b11 3
b11 ?
b11 K
b111 "
b111 $
b111 c
#240
b11 [
b10 ^
1!
1)
b11 6
b11 >
19
15
b11 B
b11 J
1H
1A
b1110 &
b1110 X
0M
1\
b11 Y
b11 a
1_
0+
0.
01
07
0:
0=
0C
0F
0I
0O
0R
0U
0Z
0]
1`
b0 '
b0 3
b0 ?
b0 K
b10 W
b1000 "
b1000 $
b1000 c
#250
b10 [
b1010 &
b1010 X
05
b1 6
b1 >
09
b10 B
b10 J
0H
1+
1.
17
1:
1C
1F
1O
1R
b1 '
b1 3
b1 ?
b1 K
b1001 "
b1001 $
b1001 c
#260
1!
0\
b1 Y
b1 a
1_
b1 [
b11 ^
0)
b11 6
b11 >
19
15
b11 B
b11 J
1H
1A
b111 &
b111 X
1M
0+
0.
11
07
0:
1=
0C
0F
1I
0O
0R
1U
b10 '
b10 3
b10 ?
b10 K
b1010 "
b1010 $
b1010 c
#270
0!
b0 Y
b0 a
0_
b1 ^
b101 &
b101 X
0A
b1 6
b1 >
09
b10 B
b10 J
0H
1+
1.
17
1:
1C
1F
1O
1R
b11 '
b11 3
b11 ?
b11 K
b1011 "
b1011 $
b1011 c
#280
b11 [
b10 ^
0!
1)
b11 6
b11 >
19
15
b11 B
b11 J
1H
1A
b1110 &
b1110 X
0M
1\
b10 Y
b10 a
0_
0+
0.
01
07
0:
0=
0C
0F
0I
0O
0R
0U
1Z
1]
b0 '
b0 3
b0 ?
b0 K
b11 W
b1100 "
b1100 $
b1100 c
#290
b0 Y
b0 a
0\
b10 [
b1010 &
b1010 X
05
b1 6
b1 >
09
b10 B
b10 J
0H
1+
1.
17
1:
1C
1F
1O
1R
b1 '
b1 3
b1 ?
b1 K
b1101 "
b1101 $
b1101 c
#300
1!
1\
b11 Y
b11 a
1_
b1 [
b11 ^
0)
b11 6
b11 >
19
15
b11 B
b11 J
1H
1A
b111 &
b111 X
1M
0+
0.
11
07
0:
1=
0C
0F
1I
0O
0R
1U
b10 '
b10 3
b10 ?
b10 K
b1110 "
b1110 $
b1110 c
#310
b1 ^
b101 &
b101 X
0A
b1 6
b1 >
09
b10 B
b10 J
0H
1+
1.
17
1:
1C
1F
1O
1R
b11 '
b11 3
b11 ?
b11 K
b1111 "
b1111 $
b1111 c
#320
b10000 c
