Lab5/MUX2to1.v
module MUX2to1(w,s0,f);
input [0:1] w;
input s0;
output reg f;

always @(w,s0) begin
    if(s0==0)
        f = w[0];
    else if(s0==1)
        f = w[1];
end

endmodule

Lab5/MUX4to1.v
`include "MUX2to1.v"
`timescale 1ns/1ns

module MUX4to1(w,s,f);

input[0:3] w;
input [1:0] s;
output f;
wire [0:1] c;
MUX2to1 MUX2to1_stage1a(w[0:1],s[0],c[0]);
MUX2to1 MUX2to1_stage1b(w[2:3],s[0],c[1]);
MUX2to1 MUX2to1_stage2(c,s[1],f);
endmodule

Lab5/MUX4to1_tb.v
`include "MUX4to1.v"
`timescale 1ns/1ns

module MUX4to1_tb();

reg[0:3] w;
reg [1:0] s;
wire f;

MUX4to1 MUX4to1_instance(w,s,f);

initial begin

    $dumpfile("MUX4to1_tb.vcd");
    $dumpvars(0,MUX4to1_tb);

    //case 1:
    w = 4'b1010; s = 2'b00;
    #10;
    w = 4'b1010; s = 2'b01;
    #10;
    w = 4'b1010; s = 2'b10;
    #10;
    w = 4'b1010;  s = 2'b11;
    #10;

    // case 2
    w = 4'b0101; s = 2'b00; 
    #10;
    w = 4'b0101; s = 2'b01; 
    #10;
    w = 4'b0101; s = 2'b10; 
    #10;
    w = 4'b0101; s = 2'b11; 
    #10;
end
endmodule

Lab5/MUX4to1_tb.vcd
$date
	Thu Aug 21 19:01:36 2025
$end
$version
	Icarus Verilog
$end
$timescale
	1ns
$end
$scope module MUX4to1_tb $end
$var wire 1 ! f $end
$var reg 2 " s [1:0] $end
$var reg 4 # w [0:3] $end
$scope module MUX4to1_instance $end
$var wire 2 $ s [1:0] $end
$var wire 4 % w [0:3] $end
$var wire 1 ! f $end
$var wire 2 & c [0:1] $end
$scope module MUX2to1_stage1a $end
$var wire 1 ' s0 $end
$var wire 2 ( w [0:1] $end
$var reg 1 ) f $end
$upscope $end
$scope module MUX2to1_stage1b $end
$var wire 1 * s0 $end
$var wire 2 + w [0:1] $end
$var reg 1 , f $end
$upscope $end
$scope module MUX2to1_stage2 $end
$var wire 1 - s0 $end
$var wire 2 . w [0:1] $end
$var reg 1 ! f $end
$upscope $end
$upscope $end
$upscope $end
$enddefinitions $end
$comment Show the parameter values. $end
$dumpall
$end
#0
$dumpvars
b11 .
0-
1,
b10 +
0*
1)
b10 (
0'
b11 &
b1010 %
b0 $
b1010 #
b0 "
1!
$end
#10
0!
0)
b0 &
b0 .
0,
1'
1*
b1 "
b1 $
#20
1!
1)
b11 &
b11 .
1,
0'
0*
1-
b10 "
b10 $
#30
0!
0)
b0 &
b0 .
0,
1'
1*
b11 "
b11 $
#40
0'
0*
0-
b1 (
b1 +
b0 "
b0 $
b101 #
b101 %
#50
1!
1)
b11 &
b11 .
1,
1'
1*
b1 "
b1 $
#60
0!
0)
b0 &
b0 .
0,
0'
0*
1-
b10 "
b10 $
#70
1!
1)
b11 &
b11 .
1,
1'
1*
b11 "
b11 $
