Lab5/mux4to1_conditional.v
module mux4to1_conditional(w,s,f);

input [0:3] w;
input [1:0] s;
output reg f;

always @(w,s) begin
    f = s[1] ? (s[0]? w[3]:w[2]):(s[0]? w[1]:w[0]);
end
endmodule

Lab5/mux4to1_conditional_tb.v
`timescale 1ns/1ns
`include "mux4to1_conditional.v"

module mux4to1_conditional_tb();

reg [0:3] w;
reg [1:0] s;
wire f;

mux4to1_conditional mux4to1_conditional(w,s,f);

initial begin

    $dumpfile("mux4to1_conditional_tb.vcd");
    $dumpvars(0,mux4to1_conditional_tb);

    //case 1:
    w = 4'b1010; s = 2'b00;
    #10;
    w = 4'b1010; s = 2'b01;
    #10;
    w = 4'b1010; s = 2'b10;
    #10;
    w = 4'b1010;  s = 2'b11;
    #10;

    // case 2
    w = 4'b0101; s = 2'b00; 
    #10;
    w = 4'b0101; s = 2'b01; 
    #10;
    w = 4'b0101; s = 2'b10; 
    #10;
    w = 4'b0101; s = 2'b11; 
    #10;
end
endmodule

Lab5/mux4to1_conditional_tb.vcd
$date
	Thu Aug 21 19:38:08 2025
$end
$version
	Icarus Verilog
$end
$timescale
	1ns
$end
$scope module mux4to1_conditional_tb $end
$var wire 1 ! f $end
$var reg 2 " s [1:0] $end
$var reg 4 # w [0:3] $end
$scope module mux4to1_conditional $end
$var wire 2 $ s [1:0] $end
$var wire 4 % w [0:3] $end
$var reg 1 ! f $end
$upscope $end
$upscope $end
$enddefinitions $end
$comment Show the parameter values. $end
$dumpall
$end
#0
$dumpvars
b1010 %
b0 $
b1010 #
b0 "
1!
$end
#10
0!
b1 "
b1 $
#20
1!
b10 "
b10 $
#30
0!
b11 "
b11 $
#40
b0 "
b0 $
b101 #
b101 %
#50
1!
b1 "
b1 $
#60
0!
b10 "
b10 $
#70
1!
b11 "
b11 $
