Lab5/MUX8to1.v
module MUX8to1(w,s,f);

input [0:7] w;
input [2:0] s;

output reg f;

always @(w,s) begin
    f = s[2] ? (s[1]?(s[0]?w[7]:w[6]):(s[0]?w[5]:w[4])):(s[1]?(s[0]?w[3]:w[2]):(s[0]?w[1]:w[0]));
end
endmodule

Lab5/MUX8to1_tb.v
`timescale 1ns/1ns
`include "MUX8to1.v"


module MUX8to1_tb();

reg[0:7] w;
reg [2:0] s;
wire f;

MUX8to1 MUX8to1_instance(w,s,f);

initial begin

    $dumpfile("MUX8to1_tb.vcd");
    $dumpvars(0,MUX8to1_tb);

    //case 1:
    w = 8'b10101101; s = 3'b000;
    #10;
    w = 8'b10101101; s = 3'b001;
    #10;
    w = 8'b10101101; s = 3'b010;
    #10;
    w = 8'b10101101;  s = 3'b011;
    #10;
    w = 8'b10101101;  s = 3'b100;
    #10;
    w = 8'b10101101;  s = 3'b101;
    #10;
    w = 8'b10101101;  s = 3'b110;
    #10;
    w = 8'b10101101;  s = 3'b111;
    #10;

    //case 1:
    w = 8'b10011100; s = 3'b000;
    #10;
    w = 8'b10011100; s = 3'b001;
    #10;
    w = 8'b10011100; s = 3'b010;
    #10;
    w = 8'b10011100;  s = 3'b011;
    #10;
    w = 8'b10011100;  s = 3'b100;
    #10;
    w = 8'b10011100;  s = 3'b101;
    #10;
    w = 8'b10011100;  s = 3'b110;
    #10;
    w = 8'b10011100;  s = 3'b111;
    #10;
end
endmodule

Lab5/MUX8to1_tb.vcd
$date
	Thu Aug 21 20:20:43 2025
$end
$version
	Icarus Verilog
$end
$timescale
	1ns
$end
$scope module MUX8to1_tb $end
$var wire 1 ! f $end
$var reg 3 " s [2:0] $end
$var reg 8 # w [0:7] $end
$scope module MUX8to1_instance $end
$var wire 3 $ s [2:0] $end
$var wire 8 % w [0:7] $end
$var reg 1 ! f $end
$upscope $end
$upscope $end
$enddefinitions $end
$comment Show the parameter values. $end
$dumpall
$end
#0
$dumpvars
b10101101 %
b0 $
b10101101 #
b0 "
1!
$end
#10
0!
b1 "
b1 $
#20
1!
b10 "
b10 $
#30
0!
b11 "
b11 $
#40
1!
b100 "
b100 $
#50
b101 "
b101 $
#60
0!
b110 "
b110 $
#70
1!
b111 "
b111 $
#80
b0 "
b0 $
b10011100 #
b10011100 %
#90
0!
b1 "
b1 $
#100
b10 "
b10 $
#110
1!
b11 "
b11 $
#120
b100 "
b100 $
#130
b101 "
b101 $
#140
0!
b110 "
b110 $
#150
b111 "
b111 $
