Lab6/Dec2to4.v
module Dec2to4(w,en,y);

input [1:0]w;
input en;
output reg [0:3]y;

always@(en,w)begin
    if(en==0) begin
        y = 4'b0000;
    end
    else if(w==0) begin
        y = 4'b1000;
    end
    else if(w==1) begin
        y = 4'b0100;
    end
    else if(w==2) begin
        y = 4'b0010;
    end
    else begin
        y = 4'b0001;
    end
end
endmodule

Lab6/Dec2to4_tb.v
`include "Dec2to4.v"
`timescale 1ns/1ns

module Dec2to4_tb();

reg [1:0]w;
reg en;
wire [0:3]y;

Dec2to4 Dec2to4_ins(w,en,y);

initial begin
    $dumpfile("Dec2to4_tb.vcd");
    $dumpvars(0,Dec2to4_tb);

    for(integer i=0; i<4; i=i+1)begin
        en=0; w = i;
        #10;
    end

    for(integer i=0; i<4; i=i+1)begin
        en=1; w = i;
        #10;
    end
end
endmodule

Lab6/Dec2to4_tb.vcd
$date
	Thu Sep 18 22:58:33 2025
$end
$version
	Icarus Verilog
$end
$timescale
	1ns
$end
$scope module Dec2to4_tb $end
$var wire 4 ! y [0:3] $end
$var reg 1 " en $end
$var reg 2 # w [1:0] $end
$scope module Dec2to4_ins $end
$var wire 1 " en $end
$var wire 2 $ w [1:0] $end
$var reg 4 % y [0:3] $end
$upscope $end
$scope begin $ivl_for_loop0 $end
$var integer 32 & i [31:0] $end
$upscope $end
$scope begin $ivl_for_loop1 $end
$var integer 32 ' i [31:0] $end
$upscope $end
$upscope $end
$enddefinitions $end
$comment Show the parameter values. $end
$dumpall
$end
#0
$dumpvars
bx '
b0 &
b0 %
b0 $
b0 #
0"
b0 !
$end
#10
b1 #
b1 $
b1 &
#20
b10 #
b10 $
b10 &
#30
b11 #
b11 $
b11 &
#40
b1000 !
b1000 %
b0 #
b0 $
1"
b0 '
b100 &
#50
b100 !
b100 %
b1 #
b1 $
b1 '
#60
b10 !
b10 %
b10 #
b10 $
b10 '
#70
b1 !
b1 %
b11 #
b11 $
b11 '
#80
b100 '
