Lab6/priority_encoder_4to2.v
module priority_encoder_4to2(w,en,y);
input [3:0]w;
output reg en;
output reg[1:0]y;

always @(w) begin
    en = 1;
    casex (w)
        4'b1xxx: y = 3;
        4'b01xx: y = 2;
        4'b001x: y = 1;
        4'b0001: y = 0; 
        default: 
        begin
            en = 0;
            y = 2'bx;      
        end
    endcase
end
endmodule

Lab6/priority_encoder_4to2_tb.v
`include "priority_encoder_4to2.v"
`timescale 1ns/1ns

module priority_encoder_4to2_tb();

reg [3:0]w;
wire en;
wire [1:0]y;

priority_encoder_4to2 priority_encoder_4to2_ins(w,en,y);

initial begin
    $dumpfile("priority_encoder_4to2_tb.vcd");
    $dumpvars(0,priority_encoder_4to2_tb);

    for(integer i=0; i<16; i=i+1)begin
        w = i; #10;
    end

end
endmodule

Lab6/priority_encoder_4to2_tb.vcd
$date
	Fri Sep 19 15:04:52 2025
$end
$version
	Icarus Verilog
$end
$timescale
	1ns
$end
$scope module priority_encoder_4to2_tb $end
$var wire 2 ! y [1:0] $end
$var wire 1 " en $end
$var reg 4 # w [3:0] $end
$scope module priority_encoder_4to2_ins $end
$var wire 4 $ w [3:0] $end
$var reg 1 " en $end
$var reg 2 % y [1:0] $end
$upscope $end
$scope begin $ivl_for_loop0 $end
$var integer 32 & i [31:0] $end
$upscope $end
$upscope $end
$enddefinitions $end
$comment Show the parameter values. $end
$dumpall
$end
#0
$dumpvars
b0 &
bx %
b0 $
b0 #
0"
bx !
$end
#10
b0 !
b0 %
1"
b1 #
b1 $
b1 &
#20
b1 !
b1 %
b10 #
b10 $
b10 &
#30
b11 #
b11 $
b11 &
#40
b10 !
b10 %
b100 #
b100 $
b100 &
#50
b101 #
b101 $
b101 &
#60
b110 #
b110 $
b110 &
#70
b111 #
b111 $
b111 &
#80
b11 !
b11 %
b1000 #
b1000 $
b1000 &
#90
b1001 #
b1001 $
b1001 &
#100
b1010 #
b1010 $
b1010 &
#110
b1011 #
b1011 $
b1011 &
#120
b1100 #
b1100 $
b1100 &
#130
b1101 #
b1101 $
b1101 &
#140
b1110 #
b1110 $
b1110 &
#150
b1111 #
b1111 $
b1111 &
#160
b10000 &
